sphinxcontrib_pecanwsme-0.11.0-py3.11-nspkg.pth
sphinxcontrib/pecanwsme/__init__.py
sphinxcontrib/pecanwsme/rest.py
sphinxcontrib_pecanwsme-0.11.0.dist-info/AUTHORS
sphinxcontrib_pecanwsme-0.11.0.dist-info/LICENSE
sphinxcontrib_pecanwsme-0.11.0.dist-info/METADATA
sphinxcontrib_pecanwsme-0.11.0.dist-info/WHEEL
sphinxcontrib_pecanwsme-0.11.0.dist-info/namespace_packages.txt
sphinxcontrib_pecanwsme-0.11.0.dist-info/pbr.json
sphinxcontrib_pecanwsme-0.11.0.dist-info/top_level.txt
sphinxcontrib_pecanwsme-0.11.0.dist-info/RECORD
