Metadata-Version: 2.1
Name: sphinxcontrib-pecanwsme
Version: 0.11.0
Summary: A Sphinx extension for documenting APIs built with Pecan and WSME
Home-page: https://github.com/sphinx-contrib/pecanwsme
Author: Doug Hellmann
Author-email: doug@doughellmann.com
Project-URL: Bug Tracker, https://github.com/sphinx-contrib/pecanwsme/issues
Project-URL: Source Code, https://github.com/sphinx-contrib/pecanwsme
Keywords: documentation,sphinx
Classifier: Development Status :: 4 - Beta
Classifier: Environment :: Console
Classifier: Intended Audience :: Developers
Classifier: Intended Audience :: Information Technology
Classifier: License :: OSI Approved :: Apache Software License
Classifier: Operating System :: OS Independent
Classifier: Programming Language :: Python
Classifier: Programming Language :: Python :: 3
Classifier: Programming Language :: Python :: 3 :: Only
Classifier: Topic :: Software Development :: Documentation
Classifier: Topic :: Documentation
Classifier: Topic :: Documentation :: Sphinx
Requires-Python: >=3.8
License-File: LICENSE
License-File: AUTHORS
Requires-Dist: sphinxcontrib-httpdomain
